[
  {
    "id": "mi_24d_hungary",
    "Name": "◔Mi-24D",
    "Rank_Info": "Ранг 5БР 9.3#1",
    "Сыграно игр": "1,247",
    "Победы": "1,228",
    "Процент побед": "98.5%",
    "Возрождения": "4,765",
    "Воздушные убийства": "3,225",
    "Наземные убийства": "44,056",
    "Морские убийства": "N/A",
    "Смерти": "4,150",
    "Убийств за возрождение": "9.92",
    "Убийств за смерть": "11.39",
    "SL за игру": "0",
    "RP за игру": "0"
  },
  {
    "id": "ab_205a_1",
    "Name": "AB205A-1",
    "Rank_Info": "Ранг 5БР 7.7#2",
    "Сыграно игр": "991",
    "Победы": "988",
    "Процент побед": "99.7%",
    "Возрождения": "3,541",
    "Воздушные убийства": "3,940",
    "Наземные убийства": "13,252",
    "Морские убийства": "N/A",
    "Смерти": "3,222",
    "Убийств за возрождение": "4.86",
    "Убийств за смерть": "5.34",
    "SL за игру": "0",
    "RP за игру": "0"
  },
  {
    "id": "a_129_d",
    "Name": "AH-129D",
    "Rank_Info": "Ранг 7БР 11.0#3",
    "Сыграно игр": "685",
    "Победы": "684",
    "Процент побед": "99.9%",
    "Возрождения": "1,793",
    "Воздушные убийства": "4,910",
    "Наземные убийства": "19,486",
    "Морские убийства": "N/A",
    "Смерти": "1,294",
    "Убийств за возрождение": "13.61",
    "Убийств за смерть": "18.85",
    "SL за игру": "0",
    "RP за игру": "0"
  },
  {
    "id": "t_129_atak",
    "Name": "T129",
    "Rank_Info": "Ранг 6БР 9.7#4¤ Премиум (пак/GE)",
    "Сыграно игр": "525",
    "Победы": "525",
    "Процент побед": "100.0%",
    "Возрождения": "1,138",
    "Воздушные убийства": "8,008",
    "Наземные убийства": "8,846",
    "Морские убийства": "N/A",
    "Смерти": "763",
    "Убийств за возрождение": "14.81",
    "Убийств за смерть": "22.09",
    "SL за игру": "0",
    "RP за игру": "0"
  },
  {
    "id": "a_129_cbt",
    "Name": "A129CBT",
    "Rank_Info": "Ранг 7БР 9.7#5",
    "Сыграно игр": "511",
    "Победы": "511",
    "Процент побед": "100.0%",
    "Возрождения": "1,269",
    "Воздушные убийства": "5,408",
    "Наземные убийства": "8,306",
    "Морские убийства": "N/A",
    "Смерти": "864",
    "Убийств за возрождение": "10.81",
    "Убийств за смерть": "15.87",
    "SL за игру": "0",
    "RP за игру": "0"
  },
  {
    "id": "mi_24v_hungary",
    "Name": "◔Mi-24V",
    "Rank_Info": "Ранг 6БР 10.0#6",
    "Сыграно игр": "435",
    "Победы": "435",
    "Процент побед": "100.0%",
    "Возрождения": "967",
    "Воздушные убийства": "527",
    "Наземные убийства": "5,531",
    "Морские убийства": "N/A",
    "Смерти": "638",
    "Убийств за возрождение": "6.26",
    "Убийств за смерть": "9.50",
    "SL за игру": "0",
    "RP за игру": "0"
  },
  {
    "id": "a_109_eoa2",
    "Name": "A.109EOA-2",
    "Rank_Info": "Ранг 6БР 8.7#7",
    "Сыграно игр": "272",
    "Победы": "270",
    "Процент побед": "99.3%",
    "Возрождения": "840",
    "Воздушные убийства": "215",
    "Наземные убийства": "11,167",
    "Морские убийства": "N/A",
    "Смерти": "685",
    "Убийств за возрождение": "13.55",
    "Убийств за смерть": "16.62",
    "SL за игру": "0",
    "RP за игру": "0"
  },
  {
    "id": "mi_24p_hungary",
    "Name": "◔Mi-24P",
    "Rank_Info": "Ранг 6БР 10.0#8¤ Премиум (пак/GE)",
    "Сыграно игр": "195",
    "Победы": "195",
    "Процент побед": "100.0%",
    "Возрождения": "548",
    "Воздушные убийства": "423",
    "Наземные убийства": "1,932",
    "Морские убийства": "N/A",
    "Смерти": "404",
    "Убийств за возрождение": "4.30",
    "Убийств за смерть": "5.83",
    "SL за игру": "0",
    "RP за игру": "0"
  },
  {
    "id": "a_129_a",
    "Name": "A-129International(p)",
    "Rank_Info": "Ранг 6БР 9.7#9¤ Премиум (пак/GE)",
    "Сыграно игр": "85",
    "Победы": "85",
    "Процент побед": "100.0%",
    "Возрождения": "165",
    "Воздушные убийства": "115",
    "Наземные убийства": "2,292",
    "Морские убийства": "N/A",
    "Смерти": "111",
    "Убийств за возрождение": "14.59",
    "Убийств за смерть": "21.68",
    "SL за игру": "0",
    "RP за игру": "0"
  }
]